.gitignore
__init__.py
_version.py
localization.py
main.py
assets/icon.png
assets/icon.svg
assets/paracopy.desktop
locales/paracopy.pot
locales/fr/LC_MESSAGES/paracopy.mo
locales/fr/LC_MESSAGES/paracopy.po
model/__init__.py
model/destination.py
model/script.py
model/settings.py
model/source.py
services/__init__.py
services/copy.py
services/destination.py
services/installation.py
services/settings.py
services/shortcut.py
services/source.py
services/storage.py
services/usb.py
services/utils.py
services/root/__init__.py
services/root/compute_occupied_space.py
services/root/copy_partition.py
services/root/create_source.py
services/root/utils.py
view/__init__.py
view/main.py
view/about/__init__.py
view/about/main.py
view/copy/__init__.py
view/copy/device.py
view/copy/main.py
view/hubs/__init__.py
view/hubs/creation.py
view/hubs/hub.py
view/hubs/main.py
view/installation/__init__.py
view/installation/main.py
view/installation/step.py
view/settings/__init__.py
view/settings/main.py
view/source/__init__.py
view/source/creation.py
view/source/list.py
view/source/main.py
view/utils/__init__.py
view/utils/banners.py
view/utils/progress.py
paracopy-1.2.3.dist-info/METADATA
paracopy-1.2.3.dist-info/WHEEL
paracopy-1.2.3.dist-info/entry_points.txt
paracopy-1.2.3.dist-info/licenses/COPYING.md
paracopy-1.2.3.dist-info/RECORD
