Metadata-Version: 2.4
Name: paracopy
Version: 1.2.3
Summary: ParaCopy is a software that aims to facilitate the parallel copy of a folder to multiple destinations (USB disks or SD cards).
Author: Pierre-Yves Genest
License: # GNU AFFERO GENERAL PUBLIC LICENSE
License-File: COPYING.md
Keywords: copy,flet,parallel copy,sd card
Classifier: Development Status :: 3 - Alpha
Classifier: Environment :: X11 Applications
Classifier: Intended Audience :: End Users/Desktop
Classifier: License :: OSI Approved :: GNU Affero General Public License v3
Classifier: Natural Language :: English
Classifier: Natural Language :: French
Classifier: Operating System :: POSIX :: Linux
Classifier: Programming Language :: Python :: 3 :: Only
Classifier: Topic :: System :: Hardware
Requires-Python: >=3.10
Requires-Dist: aiohttp>=3.11.13
Requires-Dist: babel>=2.17.0
Requires-Dist: distro>=1.9.0
Requires-Dist: flet[all]>=0.27.6
Requires-Dist: packaging>=24.2
Requires-Dist: pathvalidate>=3.2.3
Requires-Dist: pydantic>=2.10.6
Requires-Dist: pyperclip>=1.9.0
Requires-Dist: pyudev>=0.24.3
